anchorfix/__init__.py
anchorfix/__main__.py
anchorfix/_core.py
anchorfix-0.0.6.dist-info/WHEEL
anchorfix-0.0.6.dist-info/entry_points.txt
anchorfix-0.0.6.dist-info/METADATA
anchorfix-0.0.6.dist-info/RECORD
