Metadata-Version: 2.3
Name: anchorfix
Version: 0.0.6
Summary: Display Python version, executable path, and script path when run with uv
Keywords: uv,python,version,path,tool
Author: heiwa4126
Author-email: heiwa4126 <heiwa4126@gmail.com>
License: MIT License
Classifier: License :: OSI Approved :: MIT License
Classifier: Operating System :: OS Independent
Classifier: Programming Language :: Python :: 3
Requires-Dist: beautifulsoup4>=4.14.2
Requires-Python: >=3.9
Project-URL: Documentation, https://github.com/heiwa4126/anchorfix#readme
Project-URL: Issues, https://github.com/heiwa4126/anchorfix/issues
Project-URL: Source, https://github.com/heiwa4126/anchorfix
